bme/__init__.py
bme/_version.py
bme/auto.py
bme/common.py
bme/exceptions.py
bme/measurement.py
bme/py.typed
bme/bme280/__init__.py
bme/bme280/bme280.py
bme/bme280/calibration.py
bme/bmp280/__init__.py
bme/bmp280/bmp280.py
bme/bmp280/calibration.py
bme_driver-0.1.2.dist-info/LICENSE
bme_driver-0.1.2.dist-info/METADATA
bme_driver-0.1.2.dist-info/WHEEL
bme_driver-0.1.2.dist-info/top_level.txt
bme_driver-0.1.2.dist-info/RECORD
