Metadata-Version: 2.1
Name: bme-driver
Version: 0.1.2
Summary: Python driver for the Bosch BMP280 and BME280 sensors.
Author-email: Rogier van der Geer <rogier@vander-geer.nl>
License: Apache License 2.0
Project-URL: Repository, https://github.com/rogiervandergeer/bme-driver
Classifier: Intended Audience :: Developers
Classifier: Programming Language :: Python :: 3
Classifier: License :: OSI Approved :: Apache Software License
Classifier: Topic :: System :: Hardware :: Hardware Drivers
Classifier: Typing :: Typed
Requires-Python: >=3
License-File: LICENSE
Requires-Dist: smbus2 >=0.3.0
Provides-Extra: dev
Requires-Dist: pytest ; extra == 'dev'
Requires-Dist: pytest-mock ; extra == 'dev'
